ReachSample/__init__.py
ReachSample-0.1.0.dist-info/LICENSE
ReachSample-0.1.0.dist-info/METADATA
ReachSample-0.1.0.dist-info/WHEEL
ReachSample-0.1.0.dist-info/top_level.txt
ReachSample-0.1.0.dist-info/RECORD
