Metadata-Version: 2.1
Name: ReachSample
Version: 0.1.0
Summary: A python library for sampling commands within a robotic workspace, compatible with the ReachMaster experimental paradigm.
Home-page: https://github.com/throneofshadow/ReachSample
Author: Brett Nelson
Author-email: bnelson@lbl.gov
License: BSD-3-Clause-LBNL
Platform: UNKNOWN
Classifier: Development Status :: 1 - Planning
Classifier: Intended Audience :: Science/Research
Classifier: License :: OSI Approved :: BSD License
Classifier: Operating System :: POSIX :: Linux
Classifier: Programming Language :: Python :: 3
Classifier: Programming Language :: Python :: 3.7
Classifier: Programming Language :: Python :: 3.8
License-File: LICENSE
Requires-Dist: pandas
Requires-Dist: matplotlib.pyplot
Requires-Dist: unittest
Requires-Dist: numpy
Requires-Dist: os
Requires-Dist: pdb
Requires-Dist: ffmpeg
